# Python列表、集合、字典推导式深度解析

## 一、基本概念
推导式（Comprehension）是Python中一种高效构建可迭代对象的语法糖，支持列表（List）、集合（Set）、字典（Dict）三种数据结构。其核心思想是通过简洁的表达式替代传统循环结构，提升代码可读性和执行效率。

### 1.1 统一语法框架
三种推导式遵循相似的语法模板：
```python
# 列表推导式
[expression for item in iterable if condition]

# 集合推导式
{expression for item in iterable if condition}

# 字典推导式
{key_expr: value_expr for item in iterable if condition}
```

## 二、核心语法与执行流程
### 2.1 执行逻辑拆解
推导式的执行过程可分解为3个阶段（以列表推导式为例）：
1. **迭代遍历**：遍历`iterable`中的每个`item`
2. **条件过滤**：对每个`item`应用`if condition`（可选）
3. **表达式计算**：对通过过滤的`item`执行`expression`
4. **结果收集**：将计算结果按顺序存入新容器

### 2.2 多循环嵌套
支持多层循环嵌套，等价于嵌套的for循环：
```python
# 传统嵌套循环
result = []
for i in range(2):
    for j in range(3):
        result.append(i*j)

# 列表推导式实现
result = [i*j for i in range(2) for j in range(3)]  # [0,0,0,0,1,2]
```

## 三、示例代码与适用场景
### 3.1 列表推导式-数据清洗
**场景**：从原始数据中提取有效字段
```python
raw_data = ["123", "abc", "456", "def"]
# 提取数字字符串并转换为整数
numbers = [int(s) for s in raw_data if s.isdigit()]  # [123, 456]
```

### 3.2 集合推导式-去重与特征提取
**场景**：从日志中提取唯一IP地址
```python
log_lines = ["192.168.1.1 - - [01/Jan/2023]", "10.0.0.2 - - [01/Jan/2023]", "192.168.1.1 - - [02/Jan/2023]"]
# 提取唯一IP地址
unique_ips = {line.split()[0] for line in log_lines}  # {'192.168.1.1', '10.0.0.2'}
```

### 3.3 字典推导式-键值转换
**场景**：将列表转换为`{元素: 索引}`的映射
```python
fruits = ["apple", "banana", "cherry"]
index_map = {fruit: idx for idx, fruit in enumerate(fruits)}  # {'apple':0, 'banana':1, 'cherry':2}
```

## 四、底层原理与性能优化
### 4.1 CPython实现解析
通过反编译字节码（`dis`模块）可发现，推导式会被编译为`LIST_APPEND`（列表）、`SET_ADD`（集合）、`STORE_MAP`（字典）等底层操作，相比手动循环减少了函数调用开销。

**示例对比**（列表构建）：
```python
# 推导式字节码关键指令
  2           0 LOAD_CONST               1 (<code object <listcomp> at 0x...>)  
              2 LOAD_CONST               2 ('<listcomp>')
              4 MAKE_FUNCTION            0
              6 LOAD_NAME                0 (range)
              8 LOAD_CONST               3 (1000)
             10 CALL_FUNCTION            1
             12 GET_ITER
             14 CALL_FUNCTION            1
             16 STORE_NAME               1 (result)

# 传统循环字节码关键指令
  5           0 LOAD_NAME                1 (range)
              2 LOAD_CONST               1 (1000)
              4 CALL_FUNCTION            1
              6 GET_ITER
              8 FOR_ITER                12 (to 22)
             10 STORE_NAME               2 (i)
  6          12 LOAD_NAME                3 (result)
             14 LOAD_ATTR                4 (append)
             16 LOAD_NAME                2 (i)
             18 CALL_FUNCTION            1
             20 POP_TOP
             22 LOAD_CONST               0 (None)
             24 RETURN_VALUE
```
可见推导式减少了`append`方法的重复调用，性能提升约30%-50%（Python官方基准测试）。

### 4.2 性能优化建议
- **优先使用内置类型**：避免在推导式中使用自定义类的复杂方法
- **控制嵌套深度**：超过2层嵌套建议改用生成器表达式或拆分逻辑
- **利用局部变量**：将高频访问的外部变量提前赋值为局部变量（减少属性查找时间）

## 五、常见陷阱与规避
### 5.1 变量作用域陷阱
**现象**：推导式中的循环变量可能与外部变量冲突
```python
x = 10
# 错误示例：列表推导式中的x会覆盖外部变量
result = [x**2 for x in range(5)]  # x最终变为4，外部x被修改
```
**规避**：使用不同的变量名，或通过函数封装隔离作用域

### 5.2 集合/字典的无序性陷阱
**现象**：推导式生成的集合/字典元素顺序不可控
```python
# 集合推导式不保证顺序
s = {i: i*2 for i in [3,1,2]}  # 可能的输出：{3:6, 1:2, 2:4}（顺序不确定）
```
**规避**：需要有序结构时使用`collections.OrderedDict`（Python3.7+字典默认有序，但显式使用更安全）

### 5.3 内存占用陷阱
**现象**：处理大数据时，推导式会一次性生成完整容器
```python
# 错误示例：处理1000万条数据时可能内存溢出
large_list = [x**2 for x in range(10_000_000)]
```
**规避**：改用生成器表达式（`(x**2 for x in range(10_000_000))`），按需生成数据

## 六、最佳实践
1. **可读性优先**：当推导式长度超过80字符或嵌套超过2层时，改用显式循环
2. **类型明确**：集合推导式避免包含不可哈希元素（如列表），字典推导式确保键唯一性
3. **条件前置**：将过滤条件`if`放在循环后面，提升执行效率（提前过滤减少计算量）
4. **混合使用**：推导式可与生成器、`zip()`、`enumerate()`等工具结合使用

## 七、经验总结
- 推导式是Python“Pythonic”编程的典型代表，熟练掌握可显著提升代码质量
- 三种推导式的核心差异在于容器特性（列表有序可重复、集合无序唯一、字典键值对）
- 底层实现的高效性使其在数据处理、特征工程等场景中具有不可替代的优势
- 使用时需平衡简洁性与可读性，避免过度滥用导致代码难以维护

**参考资料**：
- Python官方文档：[Data Structures](https://docs.python.org/3/tutorial/datastructures.html)
- 《Fluent Python》第2章：数据结构
- CPython源码：[List Comprehension实现](https://github.com/python/cpython/blob/main/Python/listobject.c)"}}}